mgmt/__init__.py
mgmt/__main__.py
mgmt/app.py
mgmt/aws.py
mgmt/config.py
mgmt/files.py
mgmt/log.py
mgmt/utils.py
mgmt-0.7.6.dist-info/LICENSE
mgmt-0.7.6.dist-info/METADATA
mgmt-0.7.6.dist-info/WHEEL
mgmt-0.7.6.dist-info/entry_points.txt
mgmt-0.7.6.dist-info/RECORD
