Metadata-Version: 2.1
Name: mgmt
Version: 0.7.6
Summary: 
Home-page: https://github.com/will-wright-eng/media-mgmt-cli
License: GNU GPL v3.0
Author: Will Wright
Author-email: willwright@example.com
Requires-Python: >=3.8,<4.0
Classifier: Development Status :: 3 - Alpha
Classifier: Intended Audience :: Developers
Classifier: License :: OSI Approved :: GNU General Public License v3 or later (GPLv3+)
Classifier: License :: Other/Proprietary License
Classifier: Operating System :: OS Independent
Classifier: Programming Language :: Python :: 3
Classifier: Programming Language :: Python :: 3.8
Classifier: Programming Language :: Python :: 3.9
Classifier: Programming Language :: Python :: 3.10
Classifier: Programming Language :: Python :: 3.11
Classifier: Topic :: Software Development :: Libraries :: Python Modules
Requires-Dist: boto3 (>=1.26.54,<2.0.0)
Requires-Dist: botocore (>=1.29.54,<2.0.0)
Requires-Dist: certifi (>=2022.12.7,<2024.0.0)
Requires-Dist: click (>=8.1.3,<9.0.0)
Requires-Dist: jmespath (>=1.0.1,<2.0.0)
Requires-Dist: pytest (>=7.2.1,<8.0.0)
Requires-Dist: python-dateutil (>=2.8.2,<3.0.0)
Requires-Dist: python-dotenv (>=1.0.0,<2.0.0)
Requires-Dist: rarfile (>=4.0,<5.0)
Requires-Dist: rich (>=13.3.5,<14.0.0)
Requires-Dist: s3transfer (>=0.6.0,<0.7.0)
Requires-Dist: six (>=1.16.0,<2.0.0)
Requires-Dist: toml (>=0.10.2,<0.11.0)
Requires-Dist: typer (>=0.9.0,<0.10.0)
Requires-Dist: urllib3 (>=1.26.14,<2.0.0)
Project-URL: Repository, https://github.com/will-wright-eng/media-mgmt-cli
